{
  "color": {
    "$description": "Palette — The Vault brand system (design.md v1.1.0). Primitives: vault/orange/cyan/neutral/green/red/amber. Semantics: Dot Notation + Voyager transactional tokens",
    "vault-100": {
      "$type": "color",
      "$value": "#f5f0ff",
      "$description": "Vault tint 1 — near-white lavender, ghost hover backgrounds"
    },
    "vault-200": {
      "$type": "color",
      "$value": "#e8deff",
      "$description": "Vault tint 2 — light lavender, selected state backgrounds"
    },
    "vault-300": {
      "$type": "color",
      "$value": "#cfbaff",
      "$description": "Vault tint 3 — medium-light lavender"
    },
    "vault-400": {
      "$type": "color",
      "$value": "#ae8eff",
      "$description": "Vault tint 4 — medium lavender"
    },
    "vault-500": {
      "$type": "color",
      "$value": "#8460e5",
      "$description": "Vault tint 5 — medium-saturated purple"
    },
    "vault-600": {
      "$type": "color",
      "$value": "#5a35c2",
      "$description": "Vault tint 6 — strong purple"
    },
    "vault-700": {
      "$type": "color",
      "$value": "#3b1782",
      "$description": "Vault Mid (#3B1782) — gradient end, link color, action primary interactive"
    },
    "vault-800": {
      "$type": "color",
      "$value": "#2e0f70",
      "$description": "Vault Dark (#2E0F70) — overlays, hover states on dark surfaces"
    },
    "vault-900": {
      "$type": "color",
      "$value": "#22005c",
      "$description": "THE VAULT (#22005C) — BRAND ANCHOR. Navigation, primary CTAs, header, sidebar background, card accent border"
    },
    "vault-1000": {
      "$type": "color",
      "$value": "#19004a",
      "$description": "Vault deep 1 — darkest interactive vault tone"
    },
    "vault-1100": {
      "$type": "color",
      "$value": "#100030",
      "$description": "Vault deep 2"
    },
    "vault-1200": {
      "$type": "color",
      "$value": "#080018",
      "$description": "Vault deep 3 — near black with vault hue"
    },
    "orange-100": {
      "$type": "color",
      "$value": "#fff8f1",
      "$description": "En Vivo tint 1 — urgent surface, countdown background"
    },
    "orange-200": {
      "$type": "color",
      "$value": "#fee9cc",
      "$description": "En Vivo tint 2 — subtle urgency fill"
    },
    "orange-300": {
      "$type": "color",
      "$value": "#fdd8a4",
      "$description": "En Vivo tint 3 — light urgency interactive"
    },
    "orange-400": {
      "$type": "color",
      "$value": "#fbc47d",
      "$description": "En Vivo tint 4 — medium urgency fill"
    },
    "orange-500": {
      "$type": "color",
      "$value": "#f4ac59",
      "$description": "En Vivo tint 5 — near anchor"
    },
    "orange-600": {
      "$type": "color",
      "$value": "#ed8936",
      "$description": "EN VIVO (#ED8936) — ANCHOR. Live auction badges, urgent status, CTA accent, imminent timer"
    },
    "orange-700": {
      "$type": "color",
      "$value": "#d46e20",
      "$description": "En Vivo shade 1 — pressed state"
    },
    "orange-800": {
      "$type": "color",
      "$value": "#b25614",
      "$description": "En Vivo shade 2"
    },
    "orange-900": {
      "$type": "color",
      "$value": "#93420a",
      "$description": "En Vivo shade 3"
    },
    "orange-1000": {
      "$type": "color",
      "$value": "#742f04",
      "$description": "En Vivo shade 4"
    },
    "orange-1100": {
      "$type": "color",
      "$value": "#541e01",
      "$description": "En Vivo shade 5"
    },
    "orange-1200": {
      "$type": "color",
      "$value": "#351000",
      "$description": "En Vivo shade 6 — maximum contrast"
    },
    "cyan-100": {
      "$type": "color",
      "$value": "#e0feff",
      "$description": "Negociable tint 1 — near-white cyan"
    },
    "cyan-200": {
      "$type": "color",
      "$value": "#aefafe",
      "$description": "Negociable tint 2"
    },
    "cyan-300": {
      "$type": "color",
      "$value": "#70f3f6",
      "$description": "Negociable tint 3"
    },
    "cyan-400": {
      "$type": "color",
      "$value": "#30e8ec",
      "$description": "Negociable tint 4"
    },
    "cyan-500": {
      "$type": "color",
      "$value": "#00dae0",
      "$description": "Negociable tint 5 — near anchor"
    },
    "cyan-600": {
      "$type": "color",
      "$value": "#00cace",
      "$description": "NEGOCIABLE (#00CACE) — ANCHOR. Negotiable status, interactive highlights, info state"
    },
    "cyan-700": {
      "$type": "color",
      "$value": "#00a8ab",
      "$description": "Negociable shade 1"
    },
    "cyan-800": {
      "$type": "color",
      "$value": "#008688",
      "$description": "Negociable shade 2"
    },
    "cyan-900": {
      "$type": "color",
      "$value": "#006466",
      "$description": "Negociable shade 3"
    },
    "cyan-1000": {
      "$type": "color",
      "$value": "#004446",
      "$description": "Negociable shade 4"
    },
    "cyan-1100": {
      "$type": "color",
      "$value": "#002526",
      "$description": "Negociable shade 5"
    },
    "cyan-1200": {
      "$type": "color",
      "$value": "#001314",
      "$description": "Negociable shade 6 — near black"
    },
    "neutral-100": {
      "$type": "color",
      "$value": "#f8faf9",
      "$description": "Neutral 1 (#F8FAF9) — Level 0 page background. Warm off-white base canvas"
    },
    "neutral-200": {
      "$type": "color",
      "$value": "#f2f4f3",
      "$description": "Neutral 2 (#F2F4F3) — Level 1 section background. Sub-sections, sidebar content, tinted wrappers"
    },
    "neutral-300": {
      "$type": "color",
      "$value": "#eaecea",
      "$description": "Neutral 3 — subtle border alternative, hover on surfaces"
    },
    "neutral-400": {
      "$type": "color",
      "$value": "#e1e3e2",
      "$description": "Neutral 4 (#E1E3E2) — Input field background, skeleton base"
    },
    "neutral-500": {
      "$type": "color",
      "$value": "#d1d5dc",
      "$description": "Neutral 5 (#D1D5DC) — Skeleton / inactive elements, closed badge background"
    },
    "neutral-600": {
      "$type": "color",
      "$value": "#b8bec9",
      "$description": "Neutral 6 — mid-gray, subtle icon fills"
    },
    "neutral-700": {
      "$type": "color",
      "$value": "#99a1af",
      "$description": "Neutral 7 (#99A1AF) — Price label text, muted icons, placeholder text anchor"
    },
    "neutral-800": {
      "$type": "color",
      "$value": "#6b7280",
      "$description": "Neutral 8 — secondary icon, supporting metadata"
    },
    "neutral-900": {
      "$type": "color",
      "$value": "#494550",
      "$description": "Neutral 9 (#494550) — BODY TEXT ANCHOR. Card body text, secondary content, form descriptions"
    },
    "neutral-1000": {
      "$type": "color",
      "$value": "#4a5565",
      "$description": "Neutral 10 (#4A5565) — Disabled component text"
    },
    "neutral-1100": {
      "$type": "color",
      "$value": "#2f3340",
      "$description": "Neutral 11 — deep gray, high contrast secondary"
    },
    "neutral-1200": {
      "$type": "color",
      "$value": "#191c1c",
      "$description": "Neutral 12 (#191C1C) — ON SURFACE ANCHOR. Primary text — never use pure black"
    },
    "green-100": {
      "$type": "color",
      "$value": "#f0fdf6",
      "$description": "Green tint 1 — success surface"
    },
    "green-200": {
      "$type": "color",
      "$value": "#dcfcec",
      "$description": "Green tint 2"
    },
    "green-300": {
      "$type": "color",
      "$value": "#aaf0c6",
      "$description": "Green tint 3"
    },
    "green-400": {
      "$type": "color",
      "$value": "#6ee09e",
      "$description": "Green tint 4"
    },
    "green-500": {
      "$type": "color",
      "$value": "#44cf76",
      "$description": "Green tint 5 — near anchor"
    },
    "green-600": {
      "$type": "color",
      "$value": "#22c55e",
      "$description": "SUCCESS (#22C55E) — ANCHOR. Successful bid, confirmed action, market bullish signal"
    },
    "green-700": {
      "$type": "color",
      "$value": "#18aa4e",
      "$description": "Green shade 1"
    },
    "green-800": {
      "$type": "color",
      "$value": "#0f8c3e",
      "$description": "Green shade 2"
    },
    "green-900": {
      "$type": "color",
      "$value": "#08702f",
      "$description": "Green shade 3"
    },
    "green-1000": {
      "$type": "color",
      "$value": "#045521",
      "$description": "Green shade 4"
    },
    "green-1100": {
      "$type": "color",
      "$value": "#023a15",
      "$description": "Green shade 5"
    },
    "green-1200": {
      "$type": "color",
      "$value": "#012008",
      "$description": "Green shade 6 — deep green"
    },
    "red-100": {
      "$type": "color",
      "$value": "#fff1f1",
      "$description": "Red tint 1 — error surface"
    },
    "red-200": {
      "$type": "color",
      "$value": "#ffe0e0",
      "$description": "Red tint 2"
    },
    "red-300": {
      "$type": "color",
      "$value": "#ffbbbb",
      "$description": "Red tint 3"
    },
    "red-400": {
      "$type": "color",
      "$value": "#ff8e8e",
      "$description": "Red tint 4"
    },
    "red-500": {
      "$type": "color",
      "$value": "#f76969",
      "$description": "Red tint 5 — near live anchor"
    },
    "red-600": {
      "$type": "color",
      "$value": "#ef4444",
      "$description": "LIVE (#EF4444) — ANCHOR. Animated dot on live auction banners. Red = error signal ONLY, never urgency/countdown"
    },
    "red-700": {
      "$type": "color",
      "$value": "#d42c2c",
      "$description": "Red shade 1"
    },
    "red-800": {
      "$type": "color",
      "$value": "#c02020",
      "$description": "Red shade 2"
    },
    "red-900": {
      "$type": "color",
      "$value": "#ba1a1a",
      "$description": "ERROR (#BA1A1A) — ANCHOR. Failed bid, rejected action, form errors"
    },
    "red-1000": {
      "$type": "color",
      "$value": "#9a0e0e",
      "$description": "Red shade 4"
    },
    "red-1100": {
      "$type": "color",
      "$value": "#780606",
      "$description": "Red shade 5"
    },
    "red-1200": {
      "$type": "color",
      "$value": "#560202",
      "$description": "Red shade 6 — deep red"
    },
    "amber-100": {
      "$type": "color",
      "$value": "#fff8e1",
      "$description": "Amber tint 1 — warning surface"
    },
    "amber-200": {
      "$type": "color",
      "$value": "#ffedb0",
      "$description": "Amber tint 2"
    },
    "amber-300": {
      "$type": "color",
      "$value": "#ffe077",
      "$description": "Amber tint 3"
    },
    "amber-400": {
      "$type": "color",
      "$value": "#ffd13d",
      "$description": "Amber tint 4"
    },
    "amber-500": {
      "$type": "color",
      "$value": "#ffb800",
      "$description": "Amber tint 5 — near anchor"
    },
    "amber-600": {
      "$type": "color",
      "$value": "#ffa000",
      "$description": "WARNING (#FFA000) — ANCHOR. Near-expiry alert, attention needed"
    },
    "amber-700": {
      "$type": "color",
      "$value": "#e08000",
      "$description": "Amber shade 1"
    },
    "amber-800": {
      "$type": "color",
      "$value": "#c06000",
      "$description": "Amber shade 2"
    },
    "amber-900": {
      "$type": "color",
      "$value": "#a04500",
      "$description": "Amber shade 3"
    },
    "amber-1000": {
      "$type": "color",
      "$value": "#7f2d00",
      "$description": "Amber shade 4"
    },
    "amber-1100": {
      "$type": "color",
      "$value": "#5e1800",
      "$description": "Amber shade 5"
    },
    "amber-1200": {
      "$type": "color",
      "$value": "#3d0900",
      "$description": "Amber shade 6 — deep amber"
    },
    "base-white": {
      "$type": "color",
      "$value": "#ffffff",
      "$description": "Absolute white #FFFFFF — Level 2 card; inverse text/icon on Vault (semantic layer references this, never raw white)"
    },
    "base-black": {
      "$type": "color",
      "$value": "#000000",
      "$description": "Absolute black #000000 — scrim base only; never body text (No Black Rule)"
    },
    "base-scrim": {
      "$type": "color",
      "$value": "rgba(0, 0, 0, 0.5)",
      "$description": "Modal overlay — base-black at 50% opacity"
    },
    "vault-utility-ghost": {
      "$type": "color",
      "$value": "rgba(34, 0, 92, 0.1)",
      "$description": "The Vault #22005C at 10% — ghost border (DESIGN.md utility)"
    },
    "vault-utility-divider": {
      "$type": "color",
      "$value": "rgba(34, 0, 92, 0.05)",
      "$description": "The Vault #22005C at 5% — section row divider"
    },
    "red-utility-error-ghost": {
      "$type": "color",
      "$value": "rgba(186, 26, 26, 0.5)",
      "$description": "Error #BA1A1A at 50% — input error ghost border"
    },
    "neutral-utility-muted": {
      "$type": "color",
      "$value": "rgba(73, 69, 80, 0.5)",
      "$description": "Same chroma as neutral-900 at 50% alpha — tertiary / muted body (DESIGN.md Muted)"
    },
    "neutral-utility-label": {
      "$type": "color",
      "$value": "rgba(73, 69, 80, 0.4)",
      "$description": "Same chroma as neutral-900 at 40% alpha — form labels (DESIGN.md Label)"
    },
    "neutral-utility-badge-closed": {
      "$type": "color",
      "$value": "#9ca3af",
      "$description": "CERRADO badge fill (#9CA3AF) — single primitive; semantics alias only"
    },
    "base-inverse-muted": {
      "$type": "color",
      "$value": "rgba(255, 255, 255, 0.6)",
      "$description": "White 60% — secondary text on Vault/sidebar (DESIGN.md On Dark Muted)"
    },
    "base-inverse-subtle": {
      "$type": "color",
      "$value": "rgba(255, 255, 255, 0.3)",
      "$description": "White 30% — tertiary on dark surfaces (DESIGN.md On Dark Subtle)"
    }
  },
  "font": {
    "$description": "Font family primitives — 3 typefaces with distinct roles (IB Fundamentos). DESIGN.md (Stitch) alinea principalmente color; tipografía sigue este modelo salvo decisión explícita",
    "display": {
      "$type": "fontFamily",
      "$value": [
        "Plus Jakarta Sans",
        "sans-serif"
      ],
      "$description": "Display and UI font — headings, labels, CTAs, navigation. Communicates brand, modernity, premium trust"
    },
    "body": {
      "$type": "fontFamily",
      "$value": [
        "Roboto",
        "sans-serif"
      ],
      "$description": "Body and data font — paragraphs, table content, metadata, form text. Communicates legibility, density, technical precision"
    },
    "mono": {
      "$type": "fontFamily",
      "$value": [
        "Roboto Mono",
        "monospace"
      ],
      "$description": "Numeric font — prices, countdown timers, bid amounts, lot codes. Eliminates jitter on WebSocket updates via native monospaced layout"
    }
  },
  "text": {
    "$description": "Typography composite tokens — 20 locked text styles. No component creates new styles outside this set",
    "display-xl": {
      "$type": "typography",
      "$value": {
        "fontFamily": "{font.display}",
        "fontSize": "48px",
        "fontWeight": 700,
        "lineHeight": 1.1667,
        "letterSpacing": "0em"
      },
      "$description": "Display XL — hero headlines, major auction event titles. Plus Jakarta Sans 48/56 w700"
    },
    "display-lg": {
      "$type": "typography",
      "$value": {
        "fontFamily": "{font.display}",
        "fontSize": "40px",
        "fontWeight": 700,
        "lineHeight": 1.2,
        "letterSpacing": "0em"
      },
      "$description": "Display LG — section hero titles, prominent page headings. Plus Jakarta Sans 40/48 w700"
    },
    "display-md": {
      "$type": "typography",
      "$value": {
        "fontFamily": "{font.display}",
        "fontSize": "32px",
        "fontWeight": 600,
        "lineHeight": 1.25,
        "letterSpacing": "0em"
      },
      "$description": "Display MD — modal headings, feature section titles. Plus Jakarta Sans 32/40 w600"
    },
    "heading-xl": {
      "$type": "typography",
      "$value": {
        "fontFamily": "{font.display}",
        "fontSize": "28px",
        "fontWeight": 600,
        "lineHeight": 1.2857,
        "letterSpacing": "0em"
      },
      "$description": "Heading XL — primary page headings, auction lot titles. Plus Jakarta Sans 28/36 w600"
    },
    "heading-lg": {
      "$type": "typography",
      "$value": {
        "fontFamily": "{font.display}",
        "fontSize": "24px",
        "fontWeight": 600,
        "lineHeight": 1.3333,
        "letterSpacing": "0em"
      },
      "$description": "Heading LG — section headings, card headers. Plus Jakarta Sans 24/32 w600"
    },
    "heading-md": {
      "$type": "typography",
      "$value": {
        "fontFamily": "{font.display}",
        "fontSize": "20px",
        "fontWeight": 600,
        "lineHeight": 1.4,
        "letterSpacing": "0em"
      },
      "$description": "Heading MD — subsection titles, dialog headings. Plus Jakarta Sans 20/28 w600"
    },
    "heading-sm": {
      "$type": "typography",
      "$value": {
        "fontFamily": "{font.display}",
        "fontSize": "18px",
        "fontWeight": 500,
        "lineHeight": 1.3333,
        "letterSpacing": "0em"
      },
      "$description": "Heading SM — widget titles, grouped form section labels. Plus Jakarta Sans 18/24 w500"
    },
    "body-lg": {
      "$type": "typography",
      "$value": {
        "fontFamily": "{font.body}",
        "fontSize": "18px",
        "fontWeight": 400,
        "lineHeight": 1.5556,
        "letterSpacing": "0em"
      },
      "$description": "Body LG — lead copy, prominent descriptions. Roboto 18/28 w400"
    },
    "body-md": {
      "$type": "typography",
      "$value": {
        "fontFamily": "{font.body}",
        "fontSize": "16px",
        "fontWeight": 400,
        "lineHeight": 1.5,
        "letterSpacing": "0em"
      },
      "$description": "Body MD — standard body text, form input text, table cell content. Roboto 16/24 w400"
    },
    "body-sm": {
      "$type": "typography",
      "$value": {
        "fontFamily": "{font.body}",
        "fontSize": "14px",
        "fontWeight": 400,
        "lineHeight": 1.4286,
        "letterSpacing": "0em"
      },
      "$description": "Body SM — supporting copy, secondary descriptions, helper text. Roboto 14/20 w400"
    },
    "label-lg": {
      "$type": "typography",
      "$value": {
        "fontFamily": "{font.display}",
        "fontSize": "16px",
        "fontWeight": 500,
        "lineHeight": 1.5,
        "letterSpacing": "0em"
      },
      "$description": "Label LG — button labels, prominent form labels, nav items. Plus Jakarta Sans 16/24 w500"
    },
    "label-md": {
      "$type": "typography",
      "$value": {
        "fontFamily": "{font.display}",
        "fontSize": "14px",
        "fontWeight": 500,
        "lineHeight": 1.4286,
        "letterSpacing": "0em"
      },
      "$description": "Label MD — standard form labels, table column headers, chip labels. Plus Jakarta Sans 14/20 w500"
    },
    "label-sm": {
      "$type": "typography",
      "$value": {
        "fontFamily": "{font.display}",
        "fontSize": "12px",
        "fontWeight": 500,
        "lineHeight": 1.3333,
        "letterSpacing": "0em"
      },
      "$description": "Label SM — badge labels, tag text, compact UI labels. Plus Jakarta Sans 12/16 w500"
    },
    "caption": {
      "$type": "typography",
      "$value": {
        "fontFamily": "{font.body}",
        "fontSize": "12px",
        "fontWeight": 400,
        "lineHeight": 1.3333,
        "letterSpacing": "0em"
      },
      "$description": "Caption — footnotes, image captions, secondary metadata. Roboto 12/16 w400"
    },
    "overline": {
      "$type": "typography",
      "$value": {
        "fontFamily": "{font.body}",
        "fontSize": "10px",
        "fontWeight": 500,
        "lineHeight": 1.4,
        "letterSpacing": "0.08em"
      },
      "$description": "Overline — category labels, section type indicators. Roboto 10/14 w500 uppercase tracking+0.08em"
    },
    "numeric-xl": {
      "$type": "typography",
      "$value": {
        "fontFamily": "{font.mono}",
        "fontSize": "40px",
        "fontWeight": 700,
        "lineHeight": 1.2,
        "letterSpacing": "0em"
      },
      "$description": "Numeric XL — live bid price in active auction. Roboto Mono 40/48 w700 tabular-nums"
    },
    "numeric-lg": {
      "$type": "typography",
      "$value": {
        "fontFamily": "{font.mono}",
        "fontSize": "32px",
        "fontWeight": 600,
        "lineHeight": 1.25,
        "letterSpacing": "0em"
      },
      "$description": "Numeric LG — current price in auction card. Roboto Mono 32/40 w600 tabular-nums"
    },
    "numeric-md": {
      "$type": "typography",
      "$value": {
        "fontFamily": "{font.mono}",
        "fontSize": "24px",
        "fontWeight": 500,
        "lineHeight": 1.3333,
        "letterSpacing": "0em"
      },
      "$description": "Numeric MD — countdown timer display. Roboto Mono 24/32 w500 tabular-nums"
    },
    "numeric-sm": {
      "$type": "typography",
      "$value": {
        "fontFamily": "{font.mono}",
        "fontSize": "16px",
        "fontWeight": 400,
        "lineHeight": 1.5,
        "letterSpacing": "0em"
      },
      "$description": "Numeric SM — table data values, vehicle spec numbers. Roboto Mono 16/24 w400 tabular-nums"
    },
    "numeric-xs": {
      "$type": "typography",
      "$value": {
        "fontFamily": "{font.mono}",
        "fontSize": "12px",
        "fontWeight": 400,
        "lineHeight": 1.3333,
        "letterSpacing": "0em"
      },
      "$description": "Numeric XS — lot IDs, VIN fragments, metadata codes. Roboto Mono 12/16 w400 tabular-nums"
    }
  },
  "icon": {
    "$description": "Icon dimension tokens — glyph box width/height only. Pair with color.icon.* for fill. Do not use space.* for icon pixel size; use icon.size.*",
    "size": {
      "$description": "Semantic icon sizes (t-shirt). xs/sm/lg alias space scale; md is 20px for heading-sm / emphasis row alignment",
      "xs": {
        "$type": "dimension",
        "$value": "12px",
        "$description": "icon.size.xs — 12px (alias space.150). Chevrons, dense table metadata, inline with label-sm / caption"
      },
      "sm": {
        "$type": "dimension",
        "$value": "16px",
        "$description": "icon.size.sm — 16px (alias space.200). Default UI + data tables, nav items beside body-md"
      },
      "md": {
        "$type": "dimension",
        "$value": "20px",
        "$description": "icon.size.md — 20px. Aligns with heading-sm line box; primary row icons, emphasis without lg jump"
      },
      "lg": {
        "$type": "dimension",
        "$value": "24px",
        "$description": "icon.size.lg — 24px (alias space.300). Section headers, empty states, toolbar actions beside label-lg"
      }
    }
  },
  "space": {
    "100": {
      "$type": "dimension",
      "$value": "8px",
      "$description": "space.100 — 8px. BASE UNIT. Standard gap between related elements"
    },
    "150": {
      "$type": "dimension",
      "$value": "12px",
      "$description": "space.150 — 12px. Card internal padding, list item gap"
    },
    "200": {
      "$type": "dimension",
      "$value": "16px",
      "$description": "space.200 — 16px. Standard component internal padding, grid gap"
    },
    "300": {
      "$type": "dimension",
      "$value": "24px",
      "$description": "space.300 — 24px. Section horizontal padding, hero padding"
    },
    "400": {
      "$type": "dimension",
      "$value": "32px",
      "$description": "space.400 — 32px. Section vertical padding, between sections"
    },
    "600": {
      "$type": "dimension",
      "$value": "48px",
      "$description": "space.600 — 48px. Major section separation"
    },
    "800": {
      "$type": "dimension",
      "$value": "64px",
      "$description": "space.800 — 64px. Header height, sidebar brand area height"
    },
    "1000": {
      "$type": "dimension",
      "$value": "80px",
      "$description": "space.1000 — 80px. Large layout gap"
    },
    "1200": {
      "$type": "dimension",
      "$value": "96px",
      "$description": "space.1200 — 96px. Maximum layout spacing"
    },
    "$description": "Spacing scale — Atlassian multiplier model. space.100 = 8px base unit. Use these tokens exclusively; never raw pixel values",
    "025": {
      "$type": "dimension",
      "$value": "2px",
      "$description": "space.025 — 2px. Icon-to-text gap, hairline padding inside dense badges"
    },
    "050": {
      "$type": "dimension",
      "$value": "4px",
      "$description": "space.050 — 4px. Tight intra-component gap, icon padding"
    }
  },
  "radius": {
    "$description": "Border radius scale — 5 steps. Sharp edges dominate: financial platform precision over consumer softness",
    "none": {
      "$type": "dimension",
      "$value": "0px",
      "$description": "radius.none — 0px. Tables, data cells — never rounded"
    },
    "sm": {
      "$type": "dimension",
      "$value": "4px",
      "$description": "radius.sm — 4px. DEFAULT. Cards, badges, inputs, buttons, sections — almost everything"
    },
    "md": {
      "$type": "dimension",
      "$value": "8px",
      "$description": "radius.md — 8px. Reserved"
    },
    "lg": {
      "$type": "dimension",
      "$value": "16px",
      "$description": "radius.lg — 16px. Modals, drawers"
    },
    "full": {
      "$type": "dimension",
      "$value": "9999px",
      "$description": "radius.full — 9999px. Icon buttons circular (28×28, 48×48), pill badges"
    }
  },
  "shadow": {
    "$description": "Elevation shadows — exactly 2 permitted per design.md. No generic box-shadow values allowed",
    "sm": {
      "$type": "shadow",
      "$value": {
        "color": "rgba(34, 0, 92, 0.06)",
        "offsetX": "0px",
        "offsetY": "8px",
        "blur": "16px",
        "spread": "0px"
      },
      "$description": "shadow.sm — Card shadow, brand-tinted (0 8px 16px rgba(34,0,92,0.06)). All cards at rest — Vault tinted elevation"
    },
    "md": {
      "$type": "shadow",
      "$value": {
        "color": "rgba(0, 0, 0, 0.1)",
        "offsetX": "0px",
        "offsetY": "8px",
        "blur": "16px",
        "spread": "0px"
      },
      "$description": "shadow.md — Floating shadow (0 8px 16px rgba(0,0,0,0.10)). Active/hover cards, modals, popovers"
    }
  },
  "motion": {
    "$description": "Motion tokens — 4 duration levels + 2 easing curves. Financial UI: motion serves clarity, never decoration",
    "duration": {
      "instant": {
        "$type": "duration",
        "$value": "0ms",
        "$description": "motion.duration.instant — 0ms. WebSocket price/timer updates. NO fade-in: instant data = trust in data freshness"
      },
      "fast": {
        "$type": "duration",
        "$value": "100ms",
        "$description": "motion.duration.fast — 100ms. Micro-interactions: hover states, button presses, checkbox toggles"
      },
      "moderate": {
        "$type": "duration",
        "$value": "220ms",
        "$description": "motion.duration.moderate — 220ms. Component transitions: modal open/close, dropdown expand, drawer slide"
      },
      "slow": {
        "$type": "duration",
        "$value": "350ms",
        "$description": "motion.duration.slow — 350ms. Page-level transitions, skeleton to content reveal"
      }
    },
    "easing": {
      "standard": {
        "$type": "cubicBezier",
        "$value": [
          0.3,
          0,
          0,
          1
        ],
        "$description": "motion.easing.standard — cubic-bezier(0.3, 0, 0, 1). General-purpose easing per design.md"
      },
      "entrance": {
        "$type": "cubicBezier",
        "$value": [
          0,
          0,
          0.2,
          1
        ],
        "$description": "motion.easing.entrance — cubic-bezier(0, 0, 0.2, 1). Elements entering the screen: modals, drawers, notifications"
      }
    }
  }
}
